PaoxueKuaisuXuexiBaodian/README.md
PaoxueKuaisuXuexiBaodian/__init__.py
PaoxueKuaisuXuexiBaodian/__main__.py
PaoxueKuaisuXuexiBaodian/file.epub
PaoxueKuaisuXuexiBaodian/index.html
PaoxueKuaisuXuexiBaodian/css/__init__.py
PaoxueKuaisuXuexiBaodian/css/annotations.css
PaoxueKuaisuXuexiBaodian/css/main.css
PaoxueKuaisuXuexiBaodian/css/normalize.css
PaoxueKuaisuXuexiBaodian/css/popup.css
PaoxueKuaisuXuexiBaodian/font/__init__.py
PaoxueKuaisuXuexiBaodian/font/fontello.eot
PaoxueKuaisuXuexiBaodian/font/fontello.svg
PaoxueKuaisuXuexiBaodian/font/fontello.ttf
PaoxueKuaisuXuexiBaodian/font/fontello.woff
PaoxueKuaisuXuexiBaodian/img/__init__.py
PaoxueKuaisuXuexiBaodian/img/annotator-glyph-sprite.png
PaoxueKuaisuXuexiBaodian/img/annotator-icon-sprite.png
PaoxueKuaisuXuexiBaodian/img/apple-touch-icon.png
PaoxueKuaisuXuexiBaodian/img/cancelfullscreen.png
PaoxueKuaisuXuexiBaodian/img/close.png
PaoxueKuaisuXuexiBaodian/img/fullscreen.png
PaoxueKuaisuXuexiBaodian/img/loader.gif
PaoxueKuaisuXuexiBaodian/img/menu-icon.png
PaoxueKuaisuXuexiBaodian/img/save.png
PaoxueKuaisuXuexiBaodian/img/saved.png
PaoxueKuaisuXuexiBaodian/img/settings-s.png
PaoxueKuaisuXuexiBaodian/img/settings.png
PaoxueKuaisuXuexiBaodian/img/star.png
PaoxueKuaisuXuexiBaodian/js/__init__.py
PaoxueKuaisuXuexiBaodian/js/epub.js
PaoxueKuaisuXuexiBaodian/js/epub.min.js
PaoxueKuaisuXuexiBaodian/js/epub.min.map
PaoxueKuaisuXuexiBaodian/js/hooks.min.js
PaoxueKuaisuXuexiBaodian/js/hooks.min.map
PaoxueKuaisuXuexiBaodian/js/reader.js
PaoxueKuaisuXuexiBaodian/js/reader.js.map
PaoxueKuaisuXuexiBaodian/js/reader.min.js
PaoxueKuaisuXuexiBaodian/js/reader.min.map
PaoxueKuaisuXuexiBaodian/js/hooks/__init__.py
PaoxueKuaisuXuexiBaodian/js/hooks/extensions/__init__.py
PaoxueKuaisuXuexiBaodian/js/hooks/extensions/highlight.js
PaoxueKuaisuXuexiBaodian/js/libs/__init__.py
PaoxueKuaisuXuexiBaodian/js/libs/jquery.min.js
PaoxueKuaisuXuexiBaodian/js/libs/localforage.min.js
PaoxueKuaisuXuexiBaodian/js/libs/screenfull.js
paoxue_kuaisu_xuexi_baodian-2022.10.11.0.dist-info/METADATA
paoxue_kuaisu_xuexi_baodian-2022.10.11.0.dist-info/WHEEL
paoxue_kuaisu_xuexi_baodian-2022.10.11.0.dist-info/entry_points.txt
paoxue_kuaisu_xuexi_baodian-2022.10.11.0.dist-info/top_level.txt
paoxue_kuaisu_xuexi_baodian-2022.10.11.0.dist-info/RECORD
